{
    "intExample": 5,
    "strExample": "Hello!",
    "boolExample": [
        false,
        false,
        false,
        false
    ],
    "idSave": 55,
    "currentlvl": 54,
    "collects": [
        true,
        true,
        true,
        true,
        true,
        true,
        true,
        true,
        true,
        true,
        true,
        true,
        true,
        true,
        true,
        true,
        true,
        true,
        true,
        true,
        true,
        true,
        true,
        true,
        true,
        true,
        true,
        true,
        true,
        true,
        true,
        true,
        true,
        true,
        true,
        true,
        true,
        true,
        true,
        true,
        true,
        true,
        true,
        true,
        true,
        true,
        true,
        true,
        true,
        true,
        true,
        true,
        true,
        true
    ],
    "isSecondPart": true,
    "skinID": 0
}